gigachat_cli/__init__.py
gigachat_cli/__main__.py
gigachat_cli/main.py
gigachat_cli/handler/help.py
gigachat_cli/handler/model.py
gigachat_cli/handler/terminal_command.py
gigachat_cli/screens/__init__.py
gigachat_cli/screens/chat.py
gigachat_cli/screens/help.py
gigachat_cli/screens/start.py
gigachat_cli/styles/__init__.py
gigachat_cli/styles/chat.css
gigachat_cli/styles/help.css
gigachat_cli/styles/start.css
gigachat_cli/utils/__init__.py
gigachat_cli/utils/command.py
gigachat_cli/utils/config.py
gigachat_cli/utils/core.py
gigachat_cli/utils/file.py
gigachat_cli/utils/list.py
gigachat_cli/utils/openfile.py
gigachat_cli/utils/selector.py
gigachat_cli/widgets/__init__.py
gigachat_cli/widgets/banner.py
gigachat_cli/widgets/command_list.py
gigachat_cli/widgets/dir.py
gigachat_cli/widgets/file_list.py
gigachat_cli/widgets/model.py
gigachat_cli/widgets/recommend.py
gigachat_cli/widgets/selector.py
gigachat_cli/widgets/typing.py
gigachat_cli-2.3.1.dist-info/licenses/LICENSE.md
gigachat_cli-2.3.1.dist-info/METADATA
gigachat_cli-2.3.1.dist-info/WHEEL
gigachat_cli-2.3.1.dist-info/entry_points.txt
gigachat_cli-2.3.1.dist-info/top_level.txt
gigachat_cli-2.3.1.dist-info/RECORD
