Metadata-Version: 2.4
Name: gigachat-cli
Version: 2.3.1
Summary: GigaChat CLI utility
Author-email: THEChrismoth <klevindanila@ya.ru>
Project-URL: Homepage, https://gitverse.ru/THEChrismoth/GigaChat-Cli
Project-URL: Repository, https://gitverse.ru/THEChrismoth/GigaChat-Cli
Project-URL: Documentation, https://gitverse.ru/THEChrismoth/GigaChat-Cli#readme
Project-URL: Issue Tracker, https://gitverse.ru/THEChrismoth/GigaChat-Cli/tasktracker
Classifier: Programming Language :: Python :: 3
Classifier: Programming Language :: Python :: 3.13
Classifier: License :: OSI Approved :: MIT License
Classifier: Operating System :: OS Independent
Classifier: Topic :: Utilities
Classifier: Topic :: Terminals
Requires-Python: >=3.13
License-File: LICENSE.md
Requires-Dist: aiofiles>=25.1.0
Requires-Dist: asyncio>=4.0.0
Requires-Dist: importlib-resources>=6.5.2
Requires-Dist: langchain-gigachat>=0.3.12
Requires-Dist: regex>=2025.9.18
Requires-Dist: setuptools-scm>=9.2.2
Requires-Dist: textual>=6.2.0
Dynamic: license-file
